scitrack/__init__.py
scitrack-2024.10.8.dist-info/LICENSE
scitrack-2024.10.8.dist-info/WHEEL
scitrack-2024.10.8.dist-info/METADATA
scitrack-2024.10.8.dist-info/RECORD
