Metadata-Version: 2.1
Name: scitrack
Version: 2024.10.8
Summary: SciTrack provides basic logging capabilities to track scientific computations.
Home-page: https://github.com/HuttleyLab/scitrack
License: BSD-3
Keywords: science, logging
Author: Gavin Huttley
Author-email: Gavin.Huttley@anu.edu.au
Requires-Python: >=3.9
Classifier: Development Status :: 4 - Beta
Classifier: Intended Audience :: Science/Research
Classifier: License :: OSI Approved :: BSD License
Classifier: Topic :: Scientific/Engineering :: Bio-Informatics
Classifier: Topic :: Software Development :: Libraries :: Python Modules
Classifier: Operating System :: OS Independent
Classifier: Programming Language :: Python :: 3.9
Classifier: Programming Language :: Python :: 3.10
Classifier: Programming Language :: Python :: 3.11
Classifier: Programming Language :: Python :: 3.12
Classifier: Programming Language :: Python :: 3.13
Requires-Dist: numpy ; extra == "test"
Requires-Dist: pytest ; extra == "test"
Requires-Dist: pytest-cov ; extra == "test"
Requires-Dist: ruff==0.6.9 ; extra == "test"
Requires-Dist: nox ; extra == "test"
Project-URL: Bug Tracker, https://github.com/HuttleyLab/scitrack/issues
Project-URL: Documentation, https://github.com/HuttleyLab/scitrack
Project-URL: Source Code, https://github.com/HuttleyLab/scitrack
Provides-Extra: test
